{
    "arcgis": {
        "portal": {
            "private_url": "https://www.foretclimat.ca/portal",
            "admin_username": "jfaurel",
            "admin_password": "change.it"
        },
        "notebook_server": {
            "web_context_url": "https://www.foretclimat.ca/notebooks",
            "private_url": "https://www.foretclimat.ca/notebooks",
            "admin_username": "jfaurel",
            "admin_password": "change.it"
        }
    },
    "run_list": [
        "recipe[arcgis-notebooks::federation]"
    ]
}
